{
  "season": "2013-14",
  "game_id": "0021300886",
  "team_abbr": "PHI",
  "opponent_abbr": "ORL",
  "matchup": "ORL vs PHI",
  "game_date": "2014-03-02",
  "players": [
    {
      "name": "Hollis Thompson",
      "school": "Georgetown",
      "school_type": "College",
      "spriteIndex": 2,
      "team_abbrev": "PHI",
      "avatar": "02",
      "conference": "Big East Conference",
      "player_id": 203138,
      "position": "Forward",
      "country": "USA",
      "game_stats": {
        "pts": 0,
        "ast": 0,
        "reb": 0,
        "stl": 0,
        "blk": 0
      },
      "game_contribution_pct": {
        "points_pct": 0.0,
        "assists_pct": 0.0,
        "rebounds_pct": 0.0,
        "defense_pct": 0.0
      }
    },
    {
      "name": "Thaddeus Young",
      "school": "Georgia Tech",
      "school_type": "College",
      "spriteIndex": 2,
      "team_abbrev": "PHI",
      "avatar": "02",
      "conference": "Atlantic Coast Conference",
      "player_id": 201152,
      "position": "Forward",
      "country": "USA",
      "game_stats": {
        "pts": 29,
        "ast": 3,
        "reb": 8,
        "stl": 2,
        "blk": 0
      },
      "game_contribution_pct": {
        "points_pct": 0.483,
        "assists_pct": 0.231,
        "rebounds_pct": 0.267,
        "defense_pct": 0.25
      }
    },
    {
      "name": "Henry Sims",
      "school": "Georgetown",
      "school_type": "College",
      "spriteIndex": 1,
      "team_abbrev": "PHI",
      "avatar": "01",
      "conference": "Big East Conference",
      "player_id": 203156,
      "position": "Center-Forward",
      "country": "USA",
      "game_stats": {
        "pts": 12,
        "ast": 1,
        "reb": 7,
        "stl": 1,
        "blk": 1
      },
      "game_contribution_pct": {
        "points_pct": 0.2,
        "assists_pct": 0.077,
        "rebounds_pct": 0.233,
        "defense_pct": 0.25
      }
    },
    {
      "name": "James Anderson",
      "school": "Oklahoma State",
      "school_type": "College",
      "spriteIndex": 2,
      "team_abbrev": "PHI",
      "avatar": "02",
      "conference": "Big 12 Conference",
      "player_id": 202341,
      "position": "Guard-Forward",
      "country": "USA",
      "game_stats": {
        "pts": 2,
        "ast": 3,
        "reb": 4,
        "stl": 2,
        "blk": 0
      },
      "game_contribution_pct": {
        "points_pct": 0.033,
        "assists_pct": 0.231,
        "rebounds_pct": 0.133,
        "defense_pct": 0.25
      }
    },
    {
      "name": "Michael Carter-Williams",
      "school": "Syracuse",
      "school_type": "College",
      "spriteIndex": 7,
      "team_abbrev": "PHI",
      "avatar": "07",
      "conference": "Atlantic Coast Conference",
      "player_id": 203487,
      "position": "Guard",
      "country": "USA",
      "game_stats": {
        "pts": 17,
        "ast": 6,
        "reb": 11,
        "stl": 1,
        "blk": 1
      },
      "game_contribution_pct": {
        "points_pct": 0.283,
        "assists_pct": 0.462,
        "rebounds_pct": 0.367,
        "defense_pct": 0.25
      }
    }
  ]
}