{
  "answer": {
    "country": "Spain",
    "country_code": "SPA"
  },
  "match": {
    "tournament": "World Cup 2006",
    "stage": "Match",
    "opponent": "Saudi Arabia",
    "date": ""
  },
  "players": [
    {
      "jersey": 19,
      "name": "Santiago Ca\u00f1izares",
      "player_id": "7562",
      "club": {
        "name": "Valencia CF",
        "club_id": "1049",
        "badge_url": "https://tmssl.akamaized.net/images/wappen/head/1049.png"
      },
      "position": {
        "x": 49.93636363636364,
        "y": 71.0
      }
    },
    {
      "jersey": 4,
      "name": "Carlos Marchena",
      "player_id": "7572",
      "club": {
        "name": "Valencia CF",
        "club_id": "1049",
        "badge_url": "https://tmssl.akamaized.net/images/wappen/head/1049.png"
      },
      "position": {
        "x": 58.68636363636363,
        "y": 59.1
      }
    },
    {
      "jersey": 20,
      "name": "Juanito",
      "player_id": "7647",
      "club": {
        "name": "Real Betis Balompi\u00e9",
        "club_id": "150",
        "badge_url": "https://tmssl.akamaized.net/images/wappen/head/150.png"
      },
      "position": {
        "x": 41.53636363636363,
        "y": 59.1
      }
    },
    {
      "jersey": 12,
      "name": "Antonio L\u00f3pez",
      "player_id": "7723",
      "club": {
        "name": "Atl\u00e9tico de Madrid",
        "club_id": "13",
        "badge_url": "https://tmssl.akamaized.net/images/wappen/head/13.png"
      },
      "position": {
        "x": 27.186363636363637,
        "y": 57.7
      }
    },
    {
      "jersey": 2,
      "name": "M\u00edchel Salgado",
      "player_id": "7515",
      "club": {
        "name": "Real Madrid",
        "club_id": "418",
        "badge_url": "https://tmssl.akamaized.net/images/wappen/head/418.png"
      },
      "position": {
        "x": 73.03636363636363,
        "y": 57.7
      }
    },
    {
      "jersey": 6,
      "name": "David Albelda",
      "player_id": "7575",
      "club": {
        "name": "Valencia CF",
        "club_id": "1049",
        "badge_url": "https://tmssl.akamaized.net/images/wappen/head/1049.png"
      },
      "position": {
        "x": 49.93636363636364,
        "y": 42.3
      }
    },
    {
      "jersey": 13,
      "name": "Andr\u00e9s Iniesta",
      "player_id": "7600",
      "club": {
        "name": "FC Barcelona",
        "club_id": "131",
        "badge_url": "https://tmssl.akamaized.net/images/wappen/head/131.png"
      },
      "position": {
        "x": 59.03636363636363,
        "y": 34.6
      }
    },
    {
      "jersey": 18,
      "name": "Cesc F\u00e0bregas",
      "player_id": "8806",
      "club": {
        "name": "Arsenal FC",
        "club_id": "11",
        "badge_url": "https://tmssl.akamaized.net/images/wappen/head/11.png"
      },
      "position": {
        "x": 40.836363636363636,
        "y": 34.6
      }
    },
    {
      "jersey": 10,
      "name": "Jos\u00e9 Antonio Reyes",
      "player_id": "7717",
      "club": {
        "name": "Arsenal FC",
        "club_id": "11",
        "badge_url": "https://tmssl.akamaized.net/images/wappen/head/11.png"
      },
      "position": {
        "x": 32.43636363636364,
        "y": 22.0
      }
    },
    {
      "jersey": 17,
      "name": "Joaqu\u00edn",
      "player_id": "7663",
      "club": {
        "name": "Real Betis Balompi\u00e9",
        "club_id": "150",
        "badge_url": "https://tmssl.akamaized.net/images/wappen/head/150.png"
      },
      "position": {
        "x": 67.43636363636364,
        "y": 22.0
      }
    },
    {
      "jersey": 7,
      "name": "Ra\u00fal",
      "player_id": "7349",
      "club": {
        "name": "Real Madrid",
        "club_id": "418",
        "badge_url": "https://tmssl.akamaized.net/images/wappen/head/418.png"
      },
      "position": {
        "x": 49.93636363636364,
        "y": 17.1
      }
    }
  ]
}